Lab 5/mux8b.v
module mux8b(ctrl,w1,w2,w3,w4,w5,w6,w7,w8,out);

input [3:0] w1,w2,w3,w4,w5,w6,w7,w8;
input [2:0] ctrl;
output [3:0] out;
reg [3:0] d1;

// assign d1 = w1;

always @(*)
    begin
        if(ctrl[2]==0)
            begin
            if(ctrl[1]==0)
                begin
                if(ctrl[0]==0)
                d1 = w1;
                if(ctrl[0]==1)
                d1 = w2;
                end
            if(ctrl[1]==1)
                begin
                if(ctrl[0]==0)
                d1 = w3;
                if(ctrl[0]==1)
                d1 = w4;
                end
            end
        if(ctrl[2]==1)
            begin
            if(ctrl[1]==0)
                begin
                if(ctrl[0]==0)
                d1 = w5;
                if(ctrl[0]==1)
                d1 = w6;
                end
            if(ctrl[1]==1)
                begin
                if(ctrl[0]==0)
                d1 = w7;
                if(ctrl[0]==1)
                d1 = w8;
                end
            end
    end

assign out = d1;

endmodule

Lab 5/fa.v
module fa(a,b,cin,sum,carry);
input a,b,cin;
output sum,carry;
wire [2:0] w20;

xor x1(sum,a,b,cin);

and a1(w20[0],a,b);
and a1(w20[1],cin,b);
and a1(w20[2],a,cin);

or o1(carry,w20[0],w20[1],w20[2]);

endmodule

Lab 5/pllAddSub.v
`include "fa.v"

module pllAddSub(a,b,chk,sum,c);

input [3:0] a,b;
input chk;

output [3:0] c;
output [3:0] sum;
wire [3:0] b1;

xor x1(b1[0],chk,b[0]);
xor x2(b1[1],chk,b[1]);
xor x3(b1[2],chk,b[2]);
xor x4(b1[3],chk,b[3]);

fa k1(a[0],b1[0],chk,sum[0],c[0]);
fa k2(a[1],b1[1],c[0],sum[1],c[1]);
fa k3(a[2],b1[2],c[1],sum[2],c[2]);
fa k4(a[3],b1[3],c[2],sum[3],c[3]);


endmodule

Lab 5/alu.v
`include "pllAddSub.v"
`include "mux8b.v"
module alu(a,b,cin,ctrl,out,cout);

input [3:0] a,b;
input cin;
input [2:0] ctrl;

output [3:0] out;
output [3:0] cout;

wire [3:0] w1;
wire [3:0] w2;
wire [3:0] w3;
wire [3:0] w4;
wire [3:0] w5;
wire [3:0] w6;
wire [3:0] w7;
wire [3:0] w8;
wire [3:0] w9;

// Adder
pllAddSub f1(a,b,ctrl[0],w1,cout);

//SUB
pllAddSub f2(a,b,ctrl[0],w2,cout);

// OR
or o1(w3[0],a[0],b[0]);
or o2(w3[1],a[1],b[1]);
or o3(w3[2],a[2],b[2]);
or o4(w3[3],a[3],b[3]);

//AND

and r1(w4[0],a[0],b[0]);
and r2(w4[1],a[1],b[1]);
and r3(w4[2],a[2],b[2]);
and r4(w4[3],a[3],b[3]);

//shIFT LEFT

assign w5[3]=a[2];
assign w5[2]=a[1];
assign w5[1]=a[0];
assign w5[0]=0;

//shIFT RIGht

assign w6[0]=a[1];
assign w6[1]=a[2];
assign w6[2]=a[3];
assign w6[3]=0;

//ROt left

assign w7[3]=a[2];
assign w7[2]=a[1];
assign w7[1]=a[0];
assign w7[0]=a[3];

//ROt RIGht

assign w8[0]=a[1];
assign w8[1]=a[2];
assign w8[2]=a[3];
assign w8[3]=a[0];


mux8b m1(ctrl,w1,w2,w3,w4,w5,w6,w7,w8,out);

endmodule








// always @(ctrl)
//     begin
//         if(ctrl[0]==0)
//             begin
//             if(ctrl[1]==0)
//                 begin
//                 if(ctrl[2]==0)
//                 out = w1;
//                 if(ctrl[2]==1)
//                 out = w2;
//                 end
//             if(ctrl[1]==1)
//                 begin
//                 if(ctrl[2]==0)
//                 out = w3;
//                 if(ctrl[2]==1)
//                 out = w4;
//                 end
//             end
//         if(ctrl[0]==1)
//             begin
//             if(ctrl[1]==0)
//                 begin
//                 if(ctrl[2]==0)
//                 out = w5;
//                 if(ctrl[2]==1)
//                 out = w6;
//                 end
//             if(ctrl[1]==1)
//                 begin
//                 if(ctrl[2]==0)
//                 out = w7;
//                 if(ctrl[2]==1)
//                 out = w8;
//                 end
//             end
//     end

// endmodule




// wire [2:0] w11;
// wire [31:0] w22;
// not n1(w11[0],ctrl[0]);
// not n2(w11[1],ctrl[1]);
// not n3(w11[2],ctrl[2]);

// and a11(w22[3:0],w11[0],w11[1],w11[2],w1);
// and a12(w22[7:4],w11[0],w11[1],ctrl[2],w2);
// and a13(w22[11:8],w11[0],ctrl[1],w11[2],w3);
// and a14(w22[15:12],w11[0],ctrl[1],ctrl[2],w4);
// and a15(w22[19:16],ctrl[0],w11[1],w11[2],w5);
// and a16(w22[23:20],ctrl[0],w11[1],ctrl[2],w6);
// and a17(w22[27:24],ctrl[0],ctrl[1],w11[2],w7);
// and a18(w22[31:28],ctrl[0],ctrl[1],ctrl[2],w8);

// or o1(out,w22[3:0],w22[7:4],w22[11:8],w22[15:12],w22[19:16],w22[23:20],w22[27:24],w22[31:28]);

// endmodule

Lab 5/alu_tb.v
module alu_tb();

reg [3:0] I1,I2;
reg [2:0] I3;
reg I4;

wire [3:0] o;
wire [3:0] c;

initial 
begin 
$dumpfile("alu_test.vcd");
$dumpvars(0,alu_tb);
end

alu a1(I1,I2,I4,I3,o,c);

initial
begin 

I1 = 4'b 1010;
I2 = 4'b 0101;
I3 = 3'b 000;
I4 = 1'b 0;
#10;
I1 = 4'b 1010;
I2 = 4'b 0101;
I3 = 3'b 001;
I4 = 1'b 0;
#10;
I1 = 4'b 1010;
I2 = 4'b 0101;
I3 = 3'b 010;
I4 = 1'b 0;
#10;
I1 = 4'b 1010;
I2 = 4'b 0101;
I3 = 3'b 011;
I4 = 1'b 0;
#10;
I1 = 4'b 1010;
I2 = 4'b 0101;
I3 = 3'b 100;
I4 = 1'b 0;
#10;
I1 = 4'b 1010;
I2 = 4'b 0101;
I3 = 3'b 101;
I4 = 1'b 0;
#10;
I1 = 4'b 1010;
I2 = 4'b 0101;
I3 = 3'b 110;
I4 = 1'b 0;
#10;
I1 = 4'b 1010;
I2 = 4'b 0101;
I3 = 3'b 111;
I4 = 1'b 0;
#10;

end

endmodule

Lab 5/alu_test.vcd
$date
	Tue Feb 11 18:13:59 2020
$end
$version
	Icarus Verilog
$end
$timescale
	1s
$end
$scope module alu_tb $end
$var wire 4 ! c [3:0] $end
$var wire 4 " o [3:0] $end
$var reg 4 # I1 [3:0] $end
$var reg 4 $ I2 [3:0] $end
$var reg 3 % I3 [2:0] $end
$var reg 1 & I4 $end
$scope module a1 $end
$var wire 4 ' a [3:0] $end
$var wire 4 ( b [3:0] $end
$var wire 1 & cin $end
$var wire 4 ) cout [3:0] $end
$var wire 3 * ctrl [2:0] $end
$var wire 4 + w8 [3:0] $end
$var wire 4 , w7 [3:0] $end
$var wire 4 - w6 [3:0] $end
$var wire 4 . w5 [3:0] $end
$var wire 4 / w4 [3:0] $end
$var wire 4 0 w3 [3:0] $end
$var wire 4 1 w2 [3:0] $end
$var wire 4 2 w1 [3:0] $end
$var wire 4 3 out [3:0] $end
$scope module f1 $end
$var wire 4 4 a [3:0] $end
$var wire 4 5 b [3:0] $end
$var wire 4 6 c [3:0] $end
$var wire 1 7 chk $end
$var wire 4 8 sum [3:0] $end
$var wire 4 9 b1 [3:0] $end
$scope module k1 $end
$var wire 1 : a $end
$var wire 1 ; b $end
$var wire 1 < carry $end
$var wire 1 7 cin $end
$var wire 1 = sum $end
$var wire 3 > w20 [2:0] $end
$upscope $end
$scope module k2 $end
$var wire 1 ? a $end
$var wire 1 @ b $end
$var wire 1 A carry $end
$var wire 1 B cin $end
$var wire 1 C sum $end
$var wire 3 D w20 [2:0] $end
$upscope $end
$scope module k3 $end
$var wire 1 E a $end
$var wire 1 F b $end
$var wire 1 G carry $end
$var wire 1 H cin $end
$var wire 1 I sum $end
$var wire 3 J w20 [2:0] $end
$upscope $end
$scope module k4 $end
$var wire 1 K a $end
$var wire 1 L b $end
$var wire 1 M carry $end
$var wire 1 N cin $end
$var wire 1 O sum $end
$var wire 3 P w20 [2:0] $end
$upscope $end
$upscope $end
$scope module f2 $end
$var wire 4 Q a [3:0] $end
$var wire 4 R b [3:0] $end
$var wire 4 S c [3:0] $end
$var wire 1 T chk $end
$var wire 4 U sum [3:0] $end
$var wire 4 V b1 [3:0] $end
$scope module k1 $end
$var wire 1 W a $end
$var wire 1 X b $end
$var wire 1 Y carry $end
$var wire 1 T cin $end
$var wire 1 Z sum $end
$var wire 3 [ w20 [2:0] $end
$upscope $end
$scope module k2 $end
$var wire 1 \ a $end
$var wire 1 ] b $end
$var wire 1 ^ carry $end
$var wire 1 _ cin $end
$var wire 1 ` sum $end
$var wire 3 a w20 [2:0] $end
$upscope $end
$scope module k3 $end
$var wire 1 b a $end
$var wire 1 c b $end
$var wire 1 d carry $end
$var wire 1 e cin $end
$var wire 1 f sum $end
$var wire 3 g w20 [2:0] $end
$upscope $end
$scope module k4 $end
$var wire 1 h a $end
$var wire 1 i b $end
$var wire 1 j carry $end
$var wire 1 k cin $end
$var wire 1 l sum $end
$var wire 3 m w20 [2:0] $end
$upscope $end
$upscope $end
$scope module m1 $end
$var wire 3 n ctrl [2:0] $end
$var wire 4 o out [3:0] $end
$var wire 4 p w1 [3:0] $end
$var wire 4 q w2 [3:0] $end
$var wire 4 r w3 [3:0] $end
$var wire 4 s w4 [3:0] $end
$var wire 4 t w5 [3:0] $end
$var wire 4 u w6 [3:0] $end
$var wire 4 v w7 [3:0] $end
$var wire 4 w w8 [3:0] $end
$var reg 4 x d1 [3:0] $end
$upscope $end
$upscope $end
$upscope $end
$enddefinitions $end
#0
$dumpvars
b1111 x
b101 w
b101 v
b101 u
b100 t
b0 s
b1111 r
b1111 q
b1111 p
b1111 o
b0 n
b0 m
1l
0k
0j
0i
1h
b0 g
1f
0e
0d
1c
0b
b0 a
1`
0_
0^
0]
1\
b0 [
1Z
0Y
1X
0W
b101 V
b1111 U
0T
b0 S
b101 R
b1010 Q
b0 P
1O
0N
0M
0L
1K
b0 J
1I
0H
0G
1F
0E
b0 D
1C
0B
0A
0@
1?
b0 >
1=
0<
1;
0:
b101 9
b1111 8
07
b0 6
b101 5
b1010 4
b1111 3
b1111 2
b1111 1
b1111 0
b0 /
b100 .
b101 -
b101 ,
b101 +
b0 *
b0 )
b101 (
b1010 '
0&
b0 %
b101 $
b1010 #
b1111 "
b0 !
$end
#10
1H
1e
1A
1M
1^
1j
0B
0_
0C
b1 D
1I
0O
b1 P
0<
0`
b1 a
1f
0l
b1 m
b1010 !
b1010 )
b1010 6
b1010 S
0Y
0;
1@
0F
1L
0X
1]
0c
1i
b101 "
b101 3
b101 o
b101 x
b1010 9
b101 2
b101 8
b101 p
1=
b0 >
b1010 V
b101 1
b101 U
b101 q
1Z
b0 [
17
1T
b1 %
b1 *
b1 n
#20
0H
0e
0N
0k
0A
0G
0M
0^
0d
b0 !
b0 )
b0 6
b0 S
0j
1C
b0 D
1I
b0 J
1O
b0 P
1`
b0 a
1f
b0 g
1l
b0 m
1;
0@
1F
0L
1X
0]
1c
0i
b101 9
b1111 2
b1111 8
b1111 p
1=
b101 V
b1111 1
b1111 U
b1111 q
1Z
07
0T
b1111 "
b1111 3
b1111 o
b1111 x
b10 %
b10 *
b10 n
#30
1H
1e
1A
1M
1^
1j
0B
0_
0C
b1 D
1I
0O
b1 P
0<
0`
b1 a
1f
0l
b1 m
b1010 !
b1010 )
b1010 6
b1010 S
0Y
0;
1@
0F
1L
0X
1]
0c
1i
b1010 9
b101 2
b101 8
b101 p
1=
b0 >
b1010 V
b101 1
b101 U
b101 q
1Z
b0 [
17
1T
b0 "
b0 3
b0 o
b0 x
b11 %
b11 *
b11 n
#40
0H
0e
0N
0k
0A
0G
0M
0^
0d
b0 !
b0 )
b0 6
b0 S
0j
1C
b0 D
1I
b0 J
1O
b0 P
1`
b0 a
1f
b0 g
1l
b0 m
1;
0@
1F
0L
1X
0]
1c
0i
b101 9
b1111 2
b1111 8
b1111 p
1=
b101 V
b1111 1
b1111 U
b1111 q
1Z
07
0T
b100 "
b100 3
b100 o
b100 x
b100 %
b100 *
b100 n
#50
1H
1e
1A
1M
1^
1j
0B
0_
0C
b1 D
1I
0O
b1 P
0<
0`
b1 a
1f
0l
b1 m
b1010 !
b1010 )
b1010 6
b1010 S
0Y
0;
1@
0F
1L
0X
1]
0c
1i
b1010 9
b101 2
b101 8
b101 p
1=
b0 >
b1010 V
b101 1
b101 U
b101 q
1Z
b0 [
17
1T
b101 "
b101 3
b101 o
b101 x
b101 %
b101 *
b101 n
#60
0H
0e
0N
0k
0A
0G
0M
0^
0d
b0 !
b0 )
b0 6
b0 S
0j
1C
b0 D
1I
b0 J
1O
b0 P
1`
b0 a
1f
b0 g
1l
b0 m
1;
0@
1F
0L
1X
0]
1c
0i
b101 9
b1111 2
b1111 8
b1111 p
1=
b101 V
b1111 1
b1111 U
b1111 q
1Z
07
0T
b110 %
b110 *
b110 n
#70
1H
1e
1A
1M
1^
1j
0B
0_
0C
b1 D
1I
0O
b1 P
0<
0`
b1 a
1f
0l
b1 m
b1010 !
b1010 )
b1010 6
b1010 S
0Y
0;
1@
0F
1L
0X
1]
0c
1i
b1010 9
b101 2
b101 8
b101 p
1=
b0 >
b1010 V
b101 1
b101 U
b101 q
1Z
b0 [
17
1T
b111 %
b111 *
b111 n
