Lab 2/fa.v
module fa(a,b,cin,sum,carry);
input a,b,cin;
output sum,carry;
wire w1;
wire [2:0] w2;
wire w3;

xor x1(sum,a,b,cin);
//xor x2(sum,w1,cin);

and a1(w2[0],a,b);
and a1(w2[1],cin,b);
and a1(w2[2],a,cin);

or o1(carry,w2[0],w2[1],w2[2]);

endmodule

Lab 5/fa_tb.v
module fa_tb();
reg I1,I2,I3;
wire sum,carry;


initial
begin
$dumpfile("fa_test.vcd");
$dumpvars(0,fa_tb);
end
fa u1(
    .a(I1),
    .b(I2),
    .cin(I3),
    .sum(sum),
    .carry(carry)
);

initial
begin

I1 = 0;
I2 = 0;
I3 = 0;
#10;
I1 = 1;
I2 = 0;
I3 = 0;
#10;
I1 = 0;
I2 = 1;
I3 = 0;
#10;
I1 = 1;
I2 = 1;
I3 = 0;
#10;
I1 = 0;
I2 = 0;
I3 = 1;
#10;
I1 = 1;
I2 = 0;
I3 = 1;
#10;
I1 = 0;
I2 = 1;
I3 = 1;
#10;
I1 = 1;
I2 = 1;
I3 = 1;
#10;

end

endmodule

Lab 2/fa_test.vcd
$date
	Tue Jan 21 15:58:01 2020
$end
$version
	Icarus Verilog
$end
$timescale
	1s
$end
$scope module fa_tb $end
$var wire 1 ! a $end
$var wire 1 " b $end
$var wire 1 # cin $end
$var wire 1 $ sum $end
$var wire 1 % carry $end
$var reg 1 & I1 $end
$var reg 1 ' I2 $end
$var reg 1 ( I3 $end
$scope module u1 $end
$var wire 1 & a $end
$var wire 1 ' b $end
$var wire 1 % carry $end
$var wire 1 ( cin $end
$var wire 1 $ sum $end
$var wire 1 ) w1 $end
$var wire 1 * w3 $end
$var wire 3 + w2 [2:0] $end
$upscope $end
$upscope $end
$enddefinitions $end
#0
$dumpvars
b0 +
0*
0)
0(
0'
0&
0%
0$
z#
z"
z!
$end
#10
1$
1)
1&
#20
1'
0&
#30
1%
1*
0$
0)
b1 +
1&
#40
0%
0*
1$
b0 +
1(
0'
0&
#50
1%
0$
1)
b100 +
1&
#60
1*
1%
b10 +
1'
0&
#70
1$
0)
b111 +
1&
