Lab 8/fsm_seq.v
module fsm_seq(x,clk,state,out);

input x;
input clk;

output reg [3:0] state;
output reg out;



initial 
begin 
out=0; 
state = 4'b 1111; 
end
	 
always @(posedge clk)
    begin
        case({state,x})     //decreasing sequence
        5'b11110: 
            begin state = 4'b1111; out = 0; end     //0 resets the position to initial
        5'b11111: 
            begin state = 4'b1110; out = 0; end     //1 pushes down the state to the next state

        5'b11100: 
            begin state = 4'b1111; out = 0; end
        5'b11101: 
            begin state = 4'b1101; out = 0; end 

        5'b11010: 
            begin state = 4'b1111; out = 0; end
        5'b11011: 
            begin state = 4'b1100; out = 0; end 

        5'b11000: 
            begin state = 4'b1111; out = 0; end
        5'b11001: 
            begin state = 4'b1011; out = 0; end 

        5'b10110: 
            begin state = 4'b1111; out = 0; end
        5'b10111: 
            begin state = 4'b1010; out = 1; end 

        5'b10100: 
            begin state = 4'b1111; out = 0; end
        5'b10101: 
            begin state = 4'b1001; out = 0; end 

        5'b10010: 
            begin state = 4'b1111; out = 0; end
        5'b10011: 
            begin state = 4'b1000; out = 0; end 

        5'b10000: 
            begin state = 4'b1111; out = 0; end
        5'b10001: 
            begin state = 4'b0111; out = 0; end 

        5'b01110: 
            begin state = 4'b1111; out = 0; end
        5'b01111: 
            begin state = 4'b0110; out = 0; end 

        5'b01100: 
            begin state = 4'b1111; out = 0; end
        5'b01101: 
            begin state = 4'b0101; out = 0; end 

        5'b01010: 
            begin state = 4'b1111; out = 0; end
        5'b01011: 
            begin state = 4'b0100; out = 0; end 

        5'b01000: 
            begin state = 4'b1111; out = 0; end
        5'b01001: 
            begin state = 4'b0011; out = 0; end 

        5'b00110: 
            begin state = 4'b1111; out = 0; end
        5'b00111: 
            begin state = 4'b0010; out = 0; end 

        5'b00100: 
            begin state = 4'b1111; out = 0; end
        5'b00101: 
            begin state = 4'b0001; out = 0; end 

        5'b00010: 
            begin state = 4'b1111; out = 0; end
        5'b00011: 
            begin state = 4'b0000; out = 0; end 

        5'b00000: 
            begin state = 4'b1111; out = 0; end
        5'b00001: 
            begin state = 4'b1111; out = 0; end 
        endcase
	 end
endmodule

Lab 8/fsm_seq_tb.v
module fsm_seq_tb();
wire [3:0] state;
wire out;
reg x,clk;

initial 
begin
$dumpfile("fsm_seq.vcd");
$dumpvars(0,fsm_seq_tb);
end

fsm_seq f1(x,clk,state,out);

initial clk=0;
always #10 clk=~clk;
initial  
begin
x=0;

#10
x=1;

#20
x=1;

#20
x=0;

#20
x=0;

#20
x=1;

#20
x=0;

#20
x=1;

#20
x=1;

#20
x=0;

#20
x=0;

#20
x=1;

#20
x=0;

#20
x=1;

#20
x=1;

#20
x=1;

#20
x=1;

#20
x=1;

#20
x=1;

#20
x=1;

#20
x=0;

#20
x=0;

#20
x=0;

#20
x=1;
end

initial 
begin
#500 $finish;
end
endmodule

Lab 8/fsm_seq.vcd
$date
	Fri Mar 13 22:41:31 2020
$end
$version
	Icarus Verilog
$end
$timescale
	1s
$end
$scope module fsm_seq_tb $end
$var wire 4 ! state [3:0] $end
$var wire 1 " out $end
$var reg 1 # clk $end
$var reg 1 $ x $end
$scope module f1 $end
$var wire 1 # clk $end
$var wire 1 $ x $end
$var reg 1 " out $end
$var reg 4 % state [3:0] $end
$upscope $end
$upscope $end
$enddefinitions $end
#0
$dumpvars
b1111 %
0$
0#
0"
b1111 !
$end
#10
b1110 !
b1110 %
1$
1#
#20
0#
#30
b1101 !
b1101 %
1#
#40
0#
#50
b1111 !
b1111 %
1#
0$
#60
0#
#70
1#
#80
0#
#90
b1110 !
b1110 %
1#
1$
#100
0#
#110
b1111 !
b1111 %
1#
0$
#120
0#
#130
b1110 !
b1110 %
1#
1$
#140
0#
#150
b1101 !
b1101 %
1#
#160
0#
#170
b1111 !
b1111 %
1#
0$
#180
0#
#190
1#
#200
0#
#210
b1110 !
b1110 %
1#
1$
#220
0#
#230
b1111 !
b1111 %
1#
0$
#240
0#
#250
b1110 !
b1110 %
1#
1$
#260
0#
#270
b1101 !
b1101 %
1#
#280
0#
#290
b1100 !
b1100 %
1#
#300
0#
#310
b1011 !
b1011 %
1#
#320
0#
#330
1"
b1010 !
b1010 %
1#
#340
0#
#350
0"
b1001 !
b1001 %
1#
#360
0#
#370
b1000 !
b1000 %
1#
#380
0#
#390
b1111 !
b1111 %
1#
0$
#400
0#
#410
1#
#420
0#
#430
1#
#440
0#
#450
b1110 !
b1110 %
1#
1$
#460
0#
#470
b1101 !
b1101 %
1#
#480
0#
#490
b1100 !
b1100 %
1#
